Workbook

Sheet Summary
A1: AstraZeneca DCF Valuation
A2: Retrospective Discounted Cash Flow Valuation | 31 December 2025 |USD $m except per-share data
A3: Model last updated: | C3: 46316
A4: Company | B4: AstraZeneca plc | D4: Key Valuation Outputs
A5: Ticker | B5: AZN | D5: Enterprise Value | E5: =DCF!B33 -> 288302.73
A6: Valuation / Discounting Date | B6: 46022 | D6: Equity Value | E6: =DCF!B35 -> 263841.73
A7: Financials | B7: USD $m | D7: Implied Share Price | E7: =DCF!B37 -> 126.47448
A8: Share Price | B8: GBP £ per share | D8: Actual Share Price | E8: =DCF!B38 -> 137.9
D9: Implied Upside / (Downside) | E9: =DCF!B39 -> -0.082853658
A11: Key DCF Assumptions | D11: Operating Forecast
A12: WACC | B12: =WACC!B32 -> 0.078362118 | D12: Metric | E12: 2026E | F12: 2030E
A13: Terminal Growth Rate | B13: =DCF!B13 -> 0.025 | D13: Revenue | E13: =Forecast!B3 -> 62850.73 | F13: =Forecast!F3 -> 78597.287
A14: Forecast Period | B14: 2026E–2030E | D14: EBIT | E14: =Forecast!B5 -> 15084.175 | F14: =Forecast!F5 -> 19256.335
A15: 2026E Revenue Growth | B15: =Forecast!B4 -> 0.07 | D15: EBIT Margin | E15: =Forecast!B6 -> 0.24 | F15: =Forecast!F6 -> 0.245
A16: 2030E EBIT Margin | B16: =Forecast!F6 -> 0.245 | D16: FCFF | E16: =Forecast!B17 -> 13583.805 | F16: =Forecast!F17 -> 17216.762
A18: Valuation Structure | D18: Implied Valuation Multiples
A19: PV of Forecast FCFF | B19: =DCF!B9 -> 61515.2 | D19: Metric | E19: DCF Implied | F19: Market Reference*
A20: PV of Terminal Value | B20: =DCF!B17 -> 226787.53 | D20: EV / FY2025 Revenue | E20: =DCF!B33/'Historical Financials'!D3 -> 4.9081996 | F20: =(WACC!B21+DCF!B42)/'Historical Financials'!D3 -> 5.313979
A21: Terminal Value / Enterprise Value | B21: =DCF!B18 -> 0.78662984 | D21: EV / FY2025 EBITDA | E21: =DCF!B33/('Historical Financials'!D5+'Historical Financials'!D9) -> 14.990003 | F21: =(WACC!B21+DCF!B42)/('Historical Financials'!D5+'Historical Financials'!D9) -> 16.229284
D22: *Market enterprise value uses the model’s 31 December 2025 market capitalisation and net-debt and acquisition-claims definition. Both columns use subsequently published FY2025 revenue and EBITDA, consistent with the retrospective valuation approach.
A24: Key Risks & Limitations | D24: Valuation Date and Information Basis
A25: Terminal Value Concentration | B25: A substantial portion of enterprise value comes from the present value of terminal cash flows. The valuation is therefore particularly sensitive to long-term growth, profitability, reinvestment and discount-rate assumptions. | D25: This retrospective valuation discounts forecast cash flows to 31 December 2025 using FY2025 financial statements published after that date. It also uses subsequently available information where identified in the source notes. It therefore does not represent a valuation based solely on information available to investors on 31 December 2025.
A26: WACC and Terminal Growth Sensitivity: | B26: Changes in WACC and terminal growth can materially affect the implied share value. Sensitivity analysis shows alternative outcomes while holding the other specified assumptions constant.
A27: Forecast Assumptions: | B27: Revenue growth, EBIT margins, tax, depreciation and amortisation, capital investment and working capital are modelled using simplified assumptions. Actual results may differ materially.
A28: Methodology and Market Comparison | B28: The DCF is one valuation approach. The market-reference multiples use the model’s 31 December 2025 market capitalisation and net-debt and acquisition-claims definition, together with subsequently published FY2025 financials. The exit-multiple calculation provides an alternative terminal-value scenario.

Sheet Historical Financials
A1: AstraZeneca Historical Financials ($m)
B2: 2023 | C2: 2024 | D2: 2025
A3: Revenue | B3: 45811 | C3: 54073 | D3: 58739
A4: Revenue Growth | B4: N/A | C4: =C3/B3-1 -> 0.1803497 | D4: =D3/C3-1 -> 0.086290755
A5: EBIT | B5: 8193 | C5: 10003 | D5: 13743
A6: EBIT Margin | B6: =B5/B3 -> 0.17884351 | C6: =C5/C3 -> 0.18499066 | D6: =D5/D3 -> 0.23396721
A7: Tax Expense | B7: -938 | C7: -1650 | D7: -2169
A8: Net Income | B8: 5961 | C8: 7041 | D8: 10233
A9: D&A | B9: =B21 -> 4934 | C9: =C21 -> 5065 | D9: =D21 -> 5490
A10: Capital Investment | B10: -3487 | C10: -4463 | D10: -5769
A11: Operating Cash Flow | B11: 10345 | C11: 11861 | D11: 14575
A12: Cash | B12: 5840 | C12: 5488 | D12: 5711
A13: Total Debt | B13: 28622 | C13: 30295 | D13: 29622
A14: Adjusted Net Working Capital. | B14: =B41 -> -4053 | C14: =C41 -> -4304 | D14: =D41 -> -3886
A16: D&A Calculation
B17: 2023 | C17: 2024 | D17: 2025
A18: Depreciation of PP&E | B18: 733 | C18: 799 | D18: 879
A19: Depreciation of ROU assets | B19: 275 | C19: 343 | D19: 404
A20: Amortisation of intangibles | B20: 3926 | C20: 3923 | D20: 4207
A21: D&A | B21: =SUM(B18:B20) -> 4934 | C21: =SUM(C18:C20) -> 5065 | D21: =SUM(D18:D20) -> 5490
A23: Tax Rate Calculation ($m)
B24: 2023 | C24: 2024 | D24: 2025
A25: Profit Before Tax | B25: 6899 | C25: 8691 | D25: 12402
A26: Tax Expense | B26: =-B7 -> 938 | C26: =-C7 -> 1650 | D26: =-D7 -> 2169
A27: Effective Tax Rate | B27: =B26/B25 -> 0.13596173 | C27: =C26/C25 -> 0.18985157 | D27: =D26/D25 -> 0.17489115
A29: Net Working Capital Calculation ($m)
B30: 2023 | C30: 2024 | D30: 2025
A31: Inventory | B31: 5424 | C31: 5288 | D31: 6557
A32: Trade & Other Receivables | B32: 12126 | C32: 12972 | D32: 15177
A33: Trade & Other Payables | B33: -22374 | C33: -22465 | D33: -25280
A34: Provisions | B34: -1028 | C34: -1269 | D34: -686
A35: Net Working Capital | B35: =SUM(B31:B34) -> -5852 | C35: =SUM(C31:C34) -> -5474 | D35: =SUM(D31:D34) -> -4232
A38: Adjusted Working Capital | B38: 2023 | C38: 2024 | D38: 2025
A39: Add back: current contingent consideration | B39: 966 | C39: 1170 | D39: 346
A40: Add back: Acerta share-purchase liability | B40: 833 | C40: 0 | D40: 0
A41: Adjusted NWC | B41: =B35+B39+B40 -> -4053 | C41: =C35+C39+C40 -> -4304 | D41: =D35+D39+D40 -> -3886

Sheet Forecast
A1: AstraZeneca Forecast ($m)
B2: 2026E | C2: 2027E | D2: 2028E | E2: 2029E | F2: 2030E
A3: Revenue | B3: ='Historical Financials'!D3*(1+B4) -> 62850.73 | C3: =B3*(1+C4) -> 66936.027 | D3: =C3*(1+D4) -> 70952.189 | E3: =D3*(1+E4) -> 74854.559 | F3: =E3*(1+F4) -> 78597.287
A4: Revenue Growth | B4: 0.07 | C4: 0.065 | D4: 0.06 | E4: 0.055 | F4: 0.05
A5: EBIT | B5: =B3*B6 -> 15084.175 | C5: =C3*C6 -> 16231.987 | D5: =D3*D6 -> 17383.286 | E5: =E3*E6 -> 18339.367 | F5: =F3*F6 -> 19256.335
A6: EBIT Margin | B6: 0.24 | C6: 0.2425 | D6: 0.245 | E6: 0.245 | F6: 0.245
A7: Tax Rate | B7: 0.18 | C7: 0.18 | D7: 0.18 | E7: 0.18 | F7: 0.18
A8: NOPAT | B8: =B5*(1-B7) -> 12369.024 | C8: =C5*(1-C7) -> 13310.229 | D8: =D5*(1-D7) -> 14254.295 | E8: =E5*(1-E7) -> 15038.281 | F8: =F5*(1-F7) -> 15790.195
A9: D&A | B9: =B3*B10 -> 5970.8194 | C9: =C3*C10 -> 6358.9226 | D9: =D3*D10 -> 6740.458 | E9: =E3*E10 -> 7111.1832 | F9: =F3*F10 -> 7466.7423
A10: D&A % Revenue | B10: 0.095 | C10: 0.095 | D10: 0.095 | E10: 0.095 | F10: 0.095
A11: EBITDA | B11: =B5+B9 -> 21054.995 | C11: =C5+C9 -> 22590.909 | D11: =D5+D9 -> 24123.744 | E11: =E5+E9 -> 25450.55 | F11: =F5+F9 -> 26723.078
A12: Capital Investment % Revenue | B12: 0.08 | C12: 0.08 | D12: 0.08 | E12: 0.08 | F12: 0.08
A13: Capital Investment | B13: =B3*B12 -> 5028.0584 | C13: =C3*C12 -> 5354.8822 | D13: =D3*D12 -> 5676.1751 | E13: =E3*E12 -> 5988.3648 | F13: =F3*F12 -> 6287.783
A14: Adjusted Net Working Capital | B14: =B3*B15 -> -4158.02 | C14: =C3*C15 -> -4428.2913 | D14: =D3*D15 -> -4693.9888 | E14: =E3*E15 -> -4952.1582 | F14: =F3*F15 -> -5199.7661
A15: NWC % Revenue | B15: ='Historical Financials'!$D$14/'Historical Financials'!$D$3 -> -0.066157068 | C15: =$B$15 -> -0.066157068 | D15: =$B$15 -> -0.066157068 | E15: =$B$15 -> -0.066157068 | F15: =$B$15 -> -0.066157068
A16: Change in NWC | B16: =B14-'Historical Financials'!D14 -> -272.02 | C16: =C14-B14 -> -270.2713 | D16: =D14-C14 -> -265.69748 | E16: =E14-D14 -> -258.16938 | F16: =F14-E14 -> -247.60791
A17: FCFF | B17: =B8+B9-B13-B16 -> 13583.805 | C17: =C8+C9-C13-C16 -> 14584.541 | D17: =D8+D9-D13-D16 -> 15584.275 | E17: =E8+E9-E13-E16 -> 16419.269 | F17: =F8+F9-F13-F16 -> 17216.762
A19: Capital Investment Calculation ($m)
B20: 2023 | C20: 2024 | D20: 2025
A21: PP&E purchases | B21: 1361 | C21: 1924 | D21: 2810
A22: Intangible purchases | B22: 2417 | C22: 2662 | D22: 3095
A23: Less: intangible disposals | B23: -291 | C23: -123 | D23: -136
A24: Net intangible investment | B24: =B22+B23 -> 2126 | C24: =C22+C23 -> 2539 | D24: =D22+D23 -> 2959
A25: Total Capital Investment | B25: =B21+B24 -> 3487 | C25: =C21+C24 -> 4463 | D25: =D21+D24 -> 5769
A26: Capital Investment % Revenue | B26: =B25/'Historical Financials'!B3 -> 0.07611709 | C26: =C25/'Historical Financials'!C3 -> 0.082536571 | D26: =D25/'Historical Financials'!D3 -> 0.098214134
A27: NWC % Revenue | B27: ='Historical Financials'!B14/'Historical Financials'!B3 -> -0.088472201 | C27: ='Historical Financials'!C14/'Historical Financials'!C3 -> -0.079596102 | D27: ='Historical Financials'!D14/'Historical Financials'!D3 -> -0.066157068

Sheet WACC
A1: AstraZeneca WACC ($m unless stated)
A3: Cost of Equity | D3: Beta Input
A4: Risk-Free Rate | B4: 0.0418 | D4: Industry Unlevered Beta | E4: 0.89
A5: Beta | B5: =$E$4*(1+(1-B13)*B22/B21) -> 0.9651473
A6: Equity Risk Premium | B6: 0.0423
A7: Cost of Equity | B7: =B4+(B5*B6) -> 0.082625731
A9: Cost of Debt
A10: Interest Expense | B10: 1335
A11: Total Debt | B11: ='Historical Financials'!D13 -> 29622
A12: Pre-Tax Cost of Debt | B12: =B10/B11 -> 0.045067855
A13: Tax Rate | B13: =Forecast!B7 -> 0.18
A14: After-Tax Cost of Debt | B14: =B12*(1-B13) -> 0.036955641
A16: Capital Structure
A17: Share Price (£) | B17: 137.9
A18: Shares Outstanding | B18: 1550907927
A19: GBP Market Value of Equity | B19: =B17*B18/1000000 -> 213870.2
A20: GBP/USD Exchange Rate | B20: 1.3451
A21: USD Market Value of Equity | B21: =B19*B20 -> 287676.81
A22: Total Debt | B22: =B11 -> 29622
A23: Total Capital | B23: =B21+B22 -> 317298.81
A24: Equity Weight | B24: =B21/B23 -> 0.9066432
A25: Debt Weight | B25: =B22/B23 -> 0.093356795
A27: WACC
A28: Cost of Equity | B28: =B7 -> 0.082625731
A29: Equity Weight | B29: =B24 -> 0.9066432
A30: After-Tax Cost of Debt | B30: =B14 -> 0.036955641
A31: Debt Weight | B31: =B25 -> 0.093356795
A32: WACC | B32: =B29*B28+B31*B30 -> 0.078362118

Sheet DCF
A1: AstraZeneca DCF Valuation ($m unless stated)
A3: DCF Forecast
B4: 2026E | C4: 2027E | D4: 2028E | E4: 2029E | F4: 2030E
A5: FCFF | B5: =Forecast!B17 -> 13583.805 | C5: =Forecast!C17 -> 14584.541 | D5: =Forecast!D17 -> 15584.275 | E5: =Forecast!E17 -> 16419.269 | F5: =Forecast!F17 -> 17216.762
A6: Discount Period | B6: 1 | C6: 2 | D6: 3 | E6: 4 | F6: 5
A7: Discount Factor | B7: =1/(1+$B$12)^B6 -> 0.92733228 | C7: =1/(1+$B$12)^C6 -> 0.85994516 | D7: =1/(1+$B$12)^D6 -> 0.7974549 | E7: =1/(1+$B$12)^E6 -> 0.73950567 | F7: =1/(1+$B$12)^F6 -> 0.68576748
A8: PV of FCFF | B8: =B5*B7 -> 12596.7 | C8: =C5*C7 -> 12541.905 | D8: =D5*D7 -> 12427.757 | E8: =E5*E7 -> 12142.142 | F8: =F5*F7 -> 11806.696
A9: Total PV of Forecast FCFF | B9: =SUM(B8:F8) -> 61515.2
A11: Valuation Assumptions
A12: WACC | B12: =WACC!B32 -> 0.078362118
A13: Terminal Growth Rate | B13: 0.025
A15: Terminal Value
A16: Terminal Value | B16: =F5*(1+B13)/(B12-B13) -> 330706.17
A17: PV of Terminal Value | B17: =B16/(1+B12)^F6 -> 226787.53
A18: PV of Terminal Value / Enterprise Value | B18: =B17/B33 -> 0.78662984
A20: Alternative Terminal Value: Exit Multiple
A21: 2030E EBITDA | B21: =Forecast!F11 -> 26723.078
A22: Exit EBITDA Multiple | B22: 12
A23: Terminal Value - Exit Multiple | B23: =B21*B22 -> 320676.93
A24: PV of Terminal Value - Exit Multiple | B24: =B23/(1+B12)^F6 -> 219909.81
A26: Terminal Value Comparison
A27: PV of Terminal Value - Perpetuity Growth | B27: =B17 -> 226787.53
A28: PV of Terminal Value - Exit Multiple | B28: =B24 -> 219909.81
A29: Difference | B29: =B28-B27 -> -6877.7221
A30: Exit Multiple / Perpetuity Growth | B30: =B28/B27 -> 0.96967328
A32: Equity Valuation
A33: Enterprise Value | B33: =B9+B17 -> 288302.73
A34: Net Debt (Gross Debt Less Cash) | B34: =WACC!B22-'Historical Financials'!D12 -> 23911
A35: Equity Value | B35: =B33-B42 -> 263841.73
A36: Shares Outstanding | B36: =WACC!B18 -> 1550907927
A37: Implied Share Price | B37: =(B35*1000000/B36)/WACC!B20 -> 126.47448
A38: Actual Share Price | B38: =WACC!B17 -> 137.9
A39: Implied Upside/(Downside) | B39: =B37/B38-1 -> -0.082853658
A41: Acquisition Contingent Consideration | B41: 550
A42: Net Debt and Acquisition Claims | B42: =B34+B41 -> 24461

Sheet Sensitivity
A1: AstraZeneca DCF Sensitivity Analysis (£ per share)
A3: Sensitivity Analysis
A4: WACC / Terminal Growth | B4: 0.015 | C4: 0.02 | D4: 0.025 | E4: 0.03 | F4: 0.035
A5: 0.06 | B5: =((DCF!$B$5/(1+$A5)^DCF!$B$6)+(DCF!$C$5/(1+$A5)^DCF!$C$6)+(DCF!$D$5/(1+$A5)^DCF!$D$6)+(DCF!$E$5/(1+$A5)^DCF!$E$6)+(DCF!$F$5/(1+$A5)^DCF!$F$6)+((DCF!$F$5*(1+B$4)/($A5-B$4))/(1+$A5)^DCF!$F$6)-DCF!$B$42)*1000000/DCF!$B$36/WACC!$B$20 -> 158.41582 | C5: =((DCF!$B$5/(1+$A5)^DCF!$B$6)+(DCF!$C$5/(1+$A5)^DCF!$C$6)+(DCF!$D$5/(1+$A5)^DCF!$D$6)+(DCF!$E$5/(1+$A5)^DCF!$E$6)+(DCF!$F$5/(1+$A5)^DCF!$F$6)+((DCF!$F$5*(1+C$4)/($A5-C$4))/(1+$A5)^DCF!$F$6)-DCF!$B$42)*1000000/DCF!$B$36/WACC!$B$20 -> 176.57453 | D5: =((DCF!$B$5/(1+$A5)^DCF!$B$6)+(DCF!$C$5/(1+$A5)^DCF!$C$6)+(DCF!$D$5/(1+$A5)^DCF!$D$6)+(DCF!$E$5/(1+$A5)^DCF!$E$6)+(DCF!$F$5/(1+$A5)^DCF!$F$6)+((DCF!$F$5*(1+D$4)/($A5-D$4))/(1+$A5)^DCF!$F$6)-DCF!$B$42)*1000000/DCF!$B$36/WACC!$B$20 -> 199.92144 | E5: =((DCF!$B$5/(1+$A5)^DCF!$B$6)+(DCF!$C$5/(1+$A5)^DCF!$C$6)+(DCF!$D$5/(1+$A5)^DCF!$D$6)+(DCF!$E$5/(1+$A5)^DCF!$E$6)+(DCF!$F$5/(1+$A5)^DCF!$F$6)+((DCF!$F$5*(1+E$4)/($A5-E$4))/(1+$A5)^DCF!$F$6)-DCF!$B$42)*1000000/DCF!$B$36/WACC!$B$20 -> 231.05065 | F5: =((DCF!$B$5/(1+$A5)^DCF!$B$6)+(DCF!$C$5/(1+$A5)^DCF!$C$6)+(DCF!$D$5/(1+$A5)^DCF!$D$6)+(DCF!$E$5/(1+$A5)^DCF!$E$6)+(DCF!$F$5/(1+$A5)^DCF!$F$6)+((DCF!$F$5*(1+F$4)/($A5-F$4))/(1+$A5)^DCF!$F$6)-DCF!$B$42)*1000000/DCF!$B$36/WACC!$B$20 -> 274.63155
A6: 0.07 | B6: =((DCF!$B$5/(1+$A6)^DCF!$B$6)+(DCF!$C$5/(1+$A6)^DCF!$C$6)+(DCF!$D$5/(1+$A6)^DCF!$D$6)+(DCF!$E$5/(1+$A6)^DCF!$E$6)+(DCF!$F$5/(1+$A6)^DCF!$F$6)+((DCF!$F$5*(1+B$4)/($A6-B$4))/(1+$A6)^DCF!$F$6)-DCF!$B$42)*1000000/DCF!$B$36/WACC!$B$20 -> 127.0446 | C6: =((DCF!$B$5/(1+$A6)^DCF!$B$6)+(DCF!$C$5/(1+$A6)^DCF!$C$6)+(DCF!$D$5/(1+$A6)^DCF!$D$6)+(DCF!$E$5/(1+$A6)^DCF!$E$6)+(DCF!$F$5/(1+$A6)^DCF!$F$6)+((DCF!$F$5*(1+C$4)/($A6-C$4))/(1+$A6)^DCF!$F$6)-DCF!$B$42)*1000000/DCF!$B$36/WACC!$B$20 -> 138.49217 | D6: =((DCF!$B$5/(1+$A6)^DCF!$B$6)+(DCF!$C$5/(1+$A6)^DCF!$C$6)+(DCF!$D$5/(1+$A6)^DCF!$D$6)+(DCF!$E$5/(1+$A6)^DCF!$E$6)+(DCF!$F$5/(1+$A6)^DCF!$F$6)+((DCF!$F$5*(1+D$4)/($A6-D$4))/(1+$A6)^DCF!$F$6)-DCF!$B$42)*1000000/DCF!$B$36/WACC!$B$20 -> 152.48364 | E6: =((DCF!$B$5/(1+$A6)^DCF!$B$6)+(DCF!$C$5/(1+$A6)^DCF!$C$6)+(DCF!$D$5/(1+$A6)^DCF!$D$6)+(DCF!$E$5/(1+$A6)^DCF!$E$6)+(DCF!$F$5/(1+$A6)^DCF!$F$6)+((DCF!$F$5*(1+E$4)/($A6-E$4))/(1+$A6)^DCF!$F$6)-DCF!$B$42)*1000000/DCF!$B$36/WACC!$B$20 -> 169.97297 | F6: =((DCF!$B$5/(1+$A6)^DCF!$B$6)+(DCF!$C$5/(1+$A6)^DCF!$C$6)+(DCF!$D$5/(1+$A6)^DCF!$D$6)+(DCF!$E$5/(1+$A6)^DCF!$E$6)+(DCF!$F$5/(1+$A6)^DCF!$F$6)+((DCF!$F$5*(1+F$4)/($A6-F$4))/(1+$A6)^DCF!$F$6)-DCF!$B$42)*1000000/DCF!$B$36/WACC!$B$20 -> 192.45926
A7: 0.08 | B7: =((DCF!$B$5/(1+$A7)^DCF!$B$6)+(DCF!$C$5/(1+$A7)^DCF!$C$6)+(DCF!$D$5/(1+$A7)^DCF!$D$6)+(DCF!$E$5/(1+$A7)^DCF!$E$6)+(DCF!$F$5/(1+$A7)^DCF!$F$6)+((DCF!$F$5*(1+B$4)/($A7-B$4))/(1+$A7)^DCF!$F$6)-DCF!$B$42)*1000000/DCF!$B$36/WACC!$B$20 -> 105.33888 | C7: =((DCF!$B$5/(1+$A7)^DCF!$B$6)+(DCF!$C$5/(1+$A7)^DCF!$C$6)+(DCF!$D$5/(1+$A7)^DCF!$D$6)+(DCF!$E$5/(1+$A7)^DCF!$E$6)+(DCF!$F$5/(1+$A7)^DCF!$F$6)+((DCF!$F$5*(1+C$4)/($A7-C$4))/(1+$A7)^DCF!$F$6)-DCF!$B$42)*1000000/DCF!$B$36/WACC!$B$20 -> 113.11604 | D7: =((DCF!$B$5/(1+$A7)^DCF!$B$6)+(DCF!$C$5/(1+$A7)^DCF!$C$6)+(DCF!$D$5/(1+$A7)^DCF!$D$6)+(DCF!$E$5/(1+$A7)^DCF!$E$6)+(DCF!$F$5/(1+$A7)^DCF!$F$6)+((DCF!$F$5*(1+D$4)/($A7-D$4))/(1+$A7)^DCF!$F$6)-DCF!$B$42)*1000000/DCF!$B$36/WACC!$B$20 -> 122.30724 | E7: =((DCF!$B$5/(1+$A7)^DCF!$B$6)+(DCF!$C$5/(1+$A7)^DCF!$C$6)+(DCF!$D$5/(1+$A7)^DCF!$D$6)+(DCF!$E$5/(1+$A7)^DCF!$E$6)+(DCF!$F$5/(1+$A7)^DCF!$F$6)+((DCF!$F$5*(1+E$4)/($A7-E$4))/(1+$A7)^DCF!$F$6)-DCF!$B$42)*1000000/DCF!$B$36/WACC!$B$20 -> 133.33667 | F7: =((DCF!$B$5/(1+$A7)^DCF!$B$6)+(DCF!$C$5/(1+$A7)^DCF!$C$6)+(DCF!$D$5/(1+$A7)^DCF!$D$6)+(DCF!$E$5/(1+$A7)^DCF!$E$6)+(DCF!$F$5/(1+$A7)^DCF!$F$6)+((DCF!$F$5*(1+F$4)/($A7-F$4))/(1+$A7)^DCF!$F$6)-DCF!$B$42)*1000000/DCF!$B$36/WACC!$B$20 -> 146.81709
A8: 0.09 | B8: =((DCF!$B$5/(1+$A8)^DCF!$B$6)+(DCF!$C$5/(1+$A8)^DCF!$C$6)+(DCF!$D$5/(1+$A8)^DCF!$D$6)+(DCF!$E$5/(1+$A8)^DCF!$E$6)+(DCF!$F$5/(1+$A8)^DCF!$F$6)+((DCF!$F$5*(1+B$4)/($A8-B$4))/(1+$A8)^DCF!$F$6)-DCF!$B$42)*1000000/DCF!$B$36/WACC!$B$20 -> 89.431937 | C8: =((DCF!$B$5/(1+$A8)^DCF!$B$6)+(DCF!$C$5/(1+$A8)^DCF!$C$6)+(DCF!$D$5/(1+$A8)^DCF!$D$6)+(DCF!$E$5/(1+$A8)^DCF!$E$6)+(DCF!$F$5/(1+$A8)^DCF!$F$6)+((DCF!$F$5*(1+C$4)/($A8-C$4))/(1+$A8)^DCF!$F$6)-DCF!$B$42)*1000000/DCF!$B$36/WACC!$B$20 -> 95.000147 | D8: =((DCF!$B$5/(1+$A8)^DCF!$B$6)+(DCF!$C$5/(1+$A8)^DCF!$C$6)+(DCF!$D$5/(1+$A8)^DCF!$D$6)+(DCF!$E$5/(1+$A8)^DCF!$E$6)+(DCF!$F$5/(1+$A8)^DCF!$F$6)+((DCF!$F$5*(1+D$4)/($A8-D$4))/(1+$A8)^DCF!$F$6)-DCF!$B$42)*1000000/DCF!$B$36/WACC!$B$20 -> 101.425 | E8: =((DCF!$B$5/(1+$A8)^DCF!$B$6)+(DCF!$C$5/(1+$A8)^DCF!$C$6)+(DCF!$D$5/(1+$A8)^DCF!$D$6)+(DCF!$E$5/(1+$A8)^DCF!$E$6)+(DCF!$F$5/(1+$A8)^DCF!$F$6)+((DCF!$F$5*(1+E$4)/($A8-E$4))/(1+$A8)^DCF!$F$6)-DCF!$B$42)*1000000/DCF!$B$36/WACC!$B$20 -> 108.92067 | F8: =((DCF!$B$5/(1+$A8)^DCF!$B$6)+(DCF!$C$5/(1+$A8)^DCF!$C$6)+(DCF!$D$5/(1+$A8)^DCF!$D$6)+(DCF!$E$5/(1+$A8)^DCF!$E$6)+(DCF!$F$5/(1+$A8)^DCF!$F$6)+((DCF!$F$5*(1+F$4)/($A8-F$4))/(1+$A8)^DCF!$F$6)-DCF!$B$42)*1000000/DCF!$B$36/WACC!$B$20 -> 117.77919
A9: 0.1 | B9: =((DCF!$B$5/(1+$A9)^DCF!$B$6)+(DCF!$C$5/(1+$A9)^DCF!$C$6)+(DCF!$D$5/(1+$A9)^DCF!$D$6)+(DCF!$E$5/(1+$A9)^DCF!$E$6)+(DCF!$F$5/(1+$A9)^DCF!$F$6)+((DCF!$F$5*(1+B$4)/($A9-B$4))/(1+$A9)^DCF!$F$6)-DCF!$B$42)*1000000/DCF!$B$36/WACC!$B$20 -> 77.276725 | C9: =((DCF!$B$5/(1+$A9)^DCF!$B$6)+(DCF!$C$5/(1+$A9)^DCF!$C$6)+(DCF!$D$5/(1+$A9)^DCF!$D$6)+(DCF!$E$5/(1+$A9)^DCF!$E$6)+(DCF!$F$5/(1+$A9)^DCF!$F$6)+((DCF!$F$5*(1+C$4)/($A9-C$4))/(1+$A9)^DCF!$F$6)-DCF!$B$42)*1000000/DCF!$B$36/WACC!$B$20 -> 81.421503 | D9: =((DCF!$B$5/(1+$A9)^DCF!$B$6)+(DCF!$C$5/(1+$A9)^DCF!$C$6)+(DCF!$D$5/(1+$A9)^DCF!$D$6)+(DCF!$E$5/(1+$A9)^DCF!$E$6)+(DCF!$F$5/(1+$A9)^DCF!$F$6)+((DCF!$F$5*(1+D$4)/($A9-D$4))/(1+$A9)^DCF!$F$6)-DCF!$B$42)*1000000/DCF!$B$36/WACC!$B$20 -> 86.118918 | E9: =((DCF!$B$5/(1+$A9)^DCF!$B$6)+(DCF!$C$5/(1+$A9)^DCF!$C$6)+(DCF!$D$5/(1+$A9)^DCF!$D$6)+(DCF!$E$5/(1+$A9)^DCF!$E$6)+(DCF!$F$5/(1+$A9)^DCF!$F$6)+((DCF!$F$5*(1+E$4)/($A9-E$4))/(1+$A9)^DCF!$F$6)-DCF!$B$42)*1000000/DCF!$B$36/WACC!$B$20 -> 91.487392 | F9: =((DCF!$B$5/(1+$A9)^DCF!$B$6)+(DCF!$C$5/(1+$A9)^DCF!$C$6)+(DCF!$D$5/(1+$A9)^DCF!$D$6)+(DCF!$E$5/(1+$A9)^DCF!$E$6)+(DCF!$F$5/(1+$A9)^DCF!$F$6)+((DCF!$F$5*(1+F$4)/($A9-F$4))/(1+$A9)^DCF!$F$6)-DCF!$B$42)*1000000/DCF!$B$36/WACC!$B$20 -> 97.681785
A12: Implied Share Price Sensitivity: 2030E EBIT Margin and WACC
A13: WACC / 2030E EBIT Margin | B13: 0.23 | C13: 0.235 | D13: 0.24 | E13: 0.245 | F13: 0.25
A14: 0.06 | B14: =(((Forecast!$B$17/(1+$A14)^DCF!$B$6)+(Forecast!$C$17/(1+$A14)^DCF!$C$6)+(Forecast!$D$17/(1+$A14)^DCF!$D$6)+(Forecast!$E$17/(1+$A14)^DCF!$E$6)+((Forecast!$F$3*B$13*(1-Forecast!$F$7)+Forecast!$F$9-Forecast!$F$13-Forecast!$F$16)/(1+$A14)^DCF!$F$6)+(((Forecast!$F$3*B$13*(1-Forecast!$F$7)+Forecast!$F$9-Forecast!$F$13-Forecast!$F$16)*(1+DCF!$B$13)/($A14-DCF!$B$13))/(1+$A14)^DCF!$F$6)-DCF!$B$42)*1000000/DCF!$B$36/WACC!$B$20) -> 189.43373 | C14: =(((Forecast!$B$17/(1+$A14)^DCF!$B$6)+(Forecast!$C$17/(1+$A14)^DCF!$C$6)+(Forecast!$D$17/(1+$A14)^DCF!$D$6)+(Forecast!$E$17/(1+$A14)^DCF!$E$6)+((Forecast!$F$3*C$13*(1-Forecast!$F$7)+Forecast!$F$9-Forecast!$F$13-Forecast!$F$16)/(1+$A14)^DCF!$F$6)+(((Forecast!$F$3*C$13*(1-Forecast!$F$7)+Forecast!$F$9-Forecast!$F$13-Forecast!$F$16)*(1+DCF!$B$13)/($A14-DCF!$B$13))/(1+$A14)^DCF!$F$6)-DCF!$B$42)*1000000/DCF!$B$36/WACC!$B$20) -> 192.92963 | D14: =(((Forecast!$B$17/(1+$A14)^DCF!$B$6)+(Forecast!$C$17/(1+$A14)^DCF!$C$6)+(Forecast!$D$17/(1+$A14)^DCF!$D$6)+(Forecast!$E$17/(1+$A14)^DCF!$E$6)+((Forecast!$F$3*D$13*(1-Forecast!$F$7)+Forecast!$F$9-Forecast!$F$13-Forecast!$F$16)/(1+$A14)^DCF!$F$6)+(((Forecast!$F$3*D$13*(1-Forecast!$F$7)+Forecast!$F$9-Forecast!$F$13-Forecast!$F$16)*(1+DCF!$B$13)/($A14-DCF!$B$13))/(1+$A14)^DCF!$F$6)-DCF!$B$42)*1000000/DCF!$B$36/WACC!$B$20) -> 196.42554 | E14: =(((Forecast!$B$17/(1+$A14)^DCF!$B$6)+(Forecast!$C$17/(1+$A14)^DCF!$C$6)+(Forecast!$D$17/(1+$A14)^DCF!$D$6)+(Forecast!$E$17/(1+$A14)^DCF!$E$6)+((Forecast!$F$3*E$13*(1-Forecast!$F$7)+Forecast!$F$9-Forecast!$F$13-Forecast!$F$16)/(1+$A14)^DCF!$F$6)+(((Forecast!$F$3*E$13*(1-Forecast!$F$7)+Forecast!$F$9-Forecast!$F$13-Forecast!$F$16)*(1+DCF!$B$13)/($A14-DCF!$B$13))/(1+$A14)^DCF!$F$6)-DCF!$B$42)*1000000/DCF!$B$36/WACC!$B$20) -> 199.92144 | F14: =(((Forecast!$B$17/(1+$A14)^DCF!$B$6)+(Forecast!$C$17/(1+$A14)^DCF!$C$6)+(Forecast!$D$17/(1+$A14)^DCF!$D$6)+(Forecast!$E$17/(1+$A14)^DCF!$E$6)+((Forecast!$F$3*F$13*(1-Forecast!$F$7)+Forecast!$F$9-Forecast!$F$13-Forecast!$F$16)/(1+$A14)^DCF!$F$6)+(((Forecast!$F$3*F$13*(1-Forecast!$F$7)+Forecast!$F$9-Forecast!$F$13-Forecast!$F$16)*(1+DCF!$B$13)/($A14-DCF!$B$13))/(1+$A14)^DCF!$F$6)-DCF!$B$42)*1000000/DCF!$B$36/WACC!$B$20) -> 203.41734
A15: 0.07 | B15: =(((Forecast!$B$17/(1+$A15)^DCF!$B$6)+(Forecast!$C$17/(1+$A15)^DCF!$C$6)+(Forecast!$D$17/(1+$A15)^DCF!$D$6)+(Forecast!$E$17/(1+$A15)^DCF!$E$6)+((Forecast!$F$3*B$13*(1-Forecast!$F$7)+Forecast!$F$9-Forecast!$F$13-Forecast!$F$16)/(1+$A15)^DCF!$F$6)+(((Forecast!$F$3*B$13*(1-Forecast!$F$7)+Forecast!$F$9-Forecast!$F$13-Forecast!$F$16)*(1+DCF!$B$13)/($A15-DCF!$B$13))/(1+$A15)^DCF!$F$6)-DCF!$B$42)*1000000/DCF!$B$36/WACC!$B$20) -> 144.62722 | C15: =(((Forecast!$B$17/(1+$A15)^DCF!$B$6)+(Forecast!$C$17/(1+$A15)^DCF!$C$6)+(Forecast!$D$17/(1+$A15)^DCF!$D$6)+(Forecast!$E$17/(1+$A15)^DCF!$E$6)+((Forecast!$F$3*C$13*(1-Forecast!$F$7)+Forecast!$F$9-Forecast!$F$13-Forecast!$F$16)/(1+$A15)^DCF!$F$6)+(((Forecast!$F$3*C$13*(1-Forecast!$F$7)+Forecast!$F$9-Forecast!$F$13-Forecast!$F$16)*(1+DCF!$B$13)/($A15-DCF!$B$13))/(1+$A15)^DCF!$F$6)-DCF!$B$42)*1000000/DCF!$B$36/WACC!$B$20) -> 147.24603 | D15: =(((Forecast!$B$17/(1+$A15)^DCF!$B$6)+(Forecast!$C$17/(1+$A15)^DCF!$C$6)+(Forecast!$D$17/(1+$A15)^DCF!$D$6)+(Forecast!$E$17/(1+$A15)^DCF!$E$6)+((Forecast!$F$3*D$13*(1-Forecast!$F$7)+Forecast!$F$9-Forecast!$F$13-Forecast!$F$16)/(1+$A15)^DCF!$F$6)+(((Forecast!$F$3*D$13*(1-Forecast!$F$7)+Forecast!$F$9-Forecast!$F$13-Forecast!$F$16)*(1+DCF!$B$13)/($A15-DCF!$B$13))/(1+$A15)^DCF!$F$6)-DCF!$B$42)*1000000/DCF!$B$36/WACC!$B$20) -> 149.86483 | E15: =(((Forecast!$B$17/(1+$A15)^DCF!$B$6)+(Forecast!$C$17/(1+$A15)^DCF!$C$6)+(Forecast!$D$17/(1+$A15)^DCF!$D$6)+(Forecast!$E$17/(1+$A15)^DCF!$E$6)+((Forecast!$F$3*E$13*(1-Forecast!$F$7)+Forecast!$F$9-Forecast!$F$13-Forecast!$F$16)/(1+$A15)^DCF!$F$6)+(((Forecast!$F$3*E$13*(1-Forecast!$F$7)+Forecast!$F$9-Forecast!$F$13-Forecast!$F$16)*(1+DCF!$B$13)/($A15-DCF!$B$13))/(1+$A15)^DCF!$F$6)-DCF!$B$42)*1000000/DCF!$B$36/WACC!$B$20) -> 152.48364 | F15: =(((Forecast!$B$17/(1+$A15)^DCF!$B$6)+(Forecast!$C$17/(1+$A15)^DCF!$C$6)+(Forecast!$D$17/(1+$A15)^DCF!$D$6)+(Forecast!$E$17/(1+$A15)^DCF!$E$6)+((Forecast!$F$3*F$13*(1-Forecast!$F$7)+Forecast!$F$9-Forecast!$F$13-Forecast!$F$16)/(1+$A15)^DCF!$F$6)+(((Forecast!$F$3*F$13*(1-Forecast!$F$7)+Forecast!$F$9-Forecast!$F$13-Forecast!$F$16)*(1+DCF!$B$13)/($A15-DCF!$B$13))/(1+$A15)^DCF!$F$6)-DCF!$B$42)*1000000/DCF!$B$36/WACC!$B$20) -> 155.10244
A16: 0.08 | B16: =(((Forecast!$B$17/(1+$A16)^DCF!$B$6)+(Forecast!$C$17/(1+$A16)^DCF!$C$6)+(Forecast!$D$17/(1+$A16)^DCF!$D$6)+(Forecast!$E$17/(1+$A16)^DCF!$E$6)+((Forecast!$F$3*B$13*(1-Forecast!$F$7)+Forecast!$F$9-Forecast!$F$13-Forecast!$F$16)/(1+$A16)^DCF!$F$6)+(((Forecast!$F$3*B$13*(1-Forecast!$F$7)+Forecast!$F$9-Forecast!$F$13-Forecast!$F$16)*(1+DCF!$B$13)/($A16-DCF!$B$13))/(1+$A16)^DCF!$F$6)-DCF!$B$42)*1000000/DCF!$B$36/WACC!$B$20) -> 116.11405 | C16: =(((Forecast!$B$17/(1+$A16)^DCF!$B$6)+(Forecast!$C$17/(1+$A16)^DCF!$C$6)+(Forecast!$D$17/(1+$A16)^DCF!$D$6)+(Forecast!$E$17/(1+$A16)^DCF!$E$6)+((Forecast!$F$3*C$13*(1-Forecast!$F$7)+Forecast!$F$9-Forecast!$F$13-Forecast!$F$16)/(1+$A16)^DCF!$F$6)+(((Forecast!$F$3*C$13*(1-Forecast!$F$7)+Forecast!$F$9-Forecast!$F$13-Forecast!$F$16)*(1+DCF!$B$13)/($A16-DCF!$B$13))/(1+$A16)^DCF!$F$6)-DCF!$B$42)*1000000/DCF!$B$36/WACC!$B$20) -> 118.17844 | D16: =(((Forecast!$B$17/(1+$A16)^DCF!$B$6)+(Forecast!$C$17/(1+$A16)^DCF!$C$6)+(Forecast!$D$17/(1+$A16)^DCF!$D$6)+(Forecast!$E$17/(1+$A16)^DCF!$E$6)+((Forecast!$F$3*D$13*(1-Forecast!$F$7)+Forecast!$F$9-Forecast!$F$13-Forecast!$F$16)/(1+$A16)^DCF!$F$6)+(((Forecast!$F$3*D$13*(1-Forecast!$F$7)+Forecast!$F$9-Forecast!$F$13-Forecast!$F$16)*(1+DCF!$B$13)/($A16-DCF!$B$13))/(1+$A16)^DCF!$F$6)-DCF!$B$42)*1000000/DCF!$B$36/WACC!$B$20) -> 120.24284 | E16: =(((Forecast!$B$17/(1+$A16)^DCF!$B$6)+(Forecast!$C$17/(1+$A16)^DCF!$C$6)+(Forecast!$D$17/(1+$A16)^DCF!$D$6)+(Forecast!$E$17/(1+$A16)^DCF!$E$6)+((Forecast!$F$3*E$13*(1-Forecast!$F$7)+Forecast!$F$9-Forecast!$F$13-Forecast!$F$16)/(1+$A16)^DCF!$F$6)+(((Forecast!$F$3*E$13*(1-Forecast!$F$7)+Forecast!$F$9-Forecast!$F$13-Forecast!$F$16)*(1+DCF!$B$13)/($A16-DCF!$B$13))/(1+$A16)^DCF!$F$6)-DCF!$B$42)*1000000/DCF!$B$36/WACC!$B$20) -> 122.30724 | F16: =(((Forecast!$B$17/(1+$A16)^DCF!$B$6)+(Forecast!$C$17/(1+$A16)^DCF!$C$6)+(Forecast!$D$17/(1+$A16)^DCF!$D$6)+(Forecast!$E$17/(1+$A16)^DCF!$E$6)+((Forecast!$F$3*F$13*(1-Forecast!$F$7)+Forecast!$F$9-Forecast!$F$13-Forecast!$F$16)/(1+$A16)^DCF!$F$6)+(((Forecast!$F$3*F$13*(1-Forecast!$F$7)+Forecast!$F$9-Forecast!$F$13-Forecast!$F$16)*(1+DCF!$B$13)/($A16-DCF!$B$13))/(1+$A16)^DCF!$F$6)-DCF!$B$42)*1000000/DCF!$B$36/WACC!$B$20) -> 124.37163
A17: 0.09 | B17: =(((Forecast!$B$17/(1+$A17)^DCF!$B$6)+(Forecast!$C$17/(1+$A17)^DCF!$C$6)+(Forecast!$D$17/(1+$A17)^DCF!$D$6)+(Forecast!$E$17/(1+$A17)^DCF!$E$6)+((Forecast!$F$3*B$13*(1-Forecast!$F$7)+Forecast!$F$9-Forecast!$F$13-Forecast!$F$16)/(1+$A17)^DCF!$F$6)+(((Forecast!$F$3*B$13*(1-Forecast!$F$7)+Forecast!$F$9-Forecast!$F$13-Forecast!$F$16)*(1+DCF!$B$13)/($A17-DCF!$B$13))/(1+$A17)^DCF!$F$6)-DCF!$B$42)*1000000/DCF!$B$36/WACC!$B$20) -> 96.374291 | C17: =(((Forecast!$B$17/(1+$A17)^DCF!$B$6)+(Forecast!$C$17/(1+$A17)^DCF!$C$6)+(Forecast!$D$17/(1+$A17)^DCF!$D$6)+(Forecast!$E$17/(1+$A17)^DCF!$E$6)+((Forecast!$F$3*C$13*(1-Forecast!$F$7)+Forecast!$F$9-Forecast!$F$13-Forecast!$F$16)/(1+$A17)^DCF!$F$6)+(((Forecast!$F$3*C$13*(1-Forecast!$F$7)+Forecast!$F$9-Forecast!$F$13-Forecast!$F$16)*(1+DCF!$B$13)/($A17-DCF!$B$13))/(1+$A17)^DCF!$F$6)-DCF!$B$42)*1000000/DCF!$B$36/WACC!$B$20) -> 98.057862 | D17: =(((Forecast!$B$17/(1+$A17)^DCF!$B$6)+(Forecast!$C$17/(1+$A17)^DCF!$C$6)+(Forecast!$D$17/(1+$A17)^DCF!$D$6)+(Forecast!$E$17/(1+$A17)^DCF!$E$6)+((Forecast!$F$3*D$13*(1-Forecast!$F$7)+Forecast!$F$9-Forecast!$F$13-Forecast!$F$16)/(1+$A17)^DCF!$F$6)+(((Forecast!$F$3*D$13*(1-Forecast!$F$7)+Forecast!$F$9-Forecast!$F$13-Forecast!$F$16)*(1+DCF!$B$13)/($A17-DCF!$B$13))/(1+$A17)^DCF!$F$6)-DCF!$B$42)*1000000/DCF!$B$36/WACC!$B$20) -> 99.741434 | E17: =(((Forecast!$B$17/(1+$A17)^DCF!$B$6)+(Forecast!$C$17/(1+$A17)^DCF!$C$6)+(Forecast!$D$17/(1+$A17)^DCF!$D$6)+(Forecast!$E$17/(1+$A17)^DCF!$E$6)+((Forecast!$F$3*E$13*(1-Forecast!$F$7)+Forecast!$F$9-Forecast!$F$13-Forecast!$F$16)/(1+$A17)^DCF!$F$6)+(((Forecast!$F$3*E$13*(1-Forecast!$F$7)+Forecast!$F$9-Forecast!$F$13-Forecast!$F$16)*(1+DCF!$B$13)/($A17-DCF!$B$13))/(1+$A17)^DCF!$F$6)-DCF!$B$42)*1000000/DCF!$B$36/WACC!$B$20) -> 101.425 | F17: =(((Forecast!$B$17/(1+$A17)^DCF!$B$6)+(Forecast!$C$17/(1+$A17)^DCF!$C$6)+(Forecast!$D$17/(1+$A17)^DCF!$D$6)+(Forecast!$E$17/(1+$A17)^DCF!$E$6)+((Forecast!$F$3*F$13*(1-Forecast!$F$7)+Forecast!$F$9-Forecast!$F$13-Forecast!$F$16)/(1+$A17)^DCF!$F$6)+(((Forecast!$F$3*F$13*(1-Forecast!$F$7)+Forecast!$F$9-Forecast!$F$13-Forecast!$F$16)*(1+DCF!$B$13)/($A17-DCF!$B$13))/(1+$A17)^DCF!$F$6)-DCF!$B$42)*1000000/DCF!$B$36/WACC!$B$20) -> 103.10858
A18: 0.1 | B18: =(((Forecast!$B$17/(1+$A18)^DCF!$B$6)+(Forecast!$C$17/(1+$A18)^DCF!$C$6)+(Forecast!$D$17/(1+$A18)^DCF!$D$6)+(Forecast!$E$17/(1+$A18)^DCF!$E$6)+((Forecast!$F$3*B$13*(1-Forecast!$F$7)+Forecast!$F$9-Forecast!$F$13-Forecast!$F$16)/(1+$A18)^DCF!$F$6)+(((Forecast!$F$3*B$13*(1-Forecast!$F$7)+Forecast!$F$9-Forecast!$F$13-Forecast!$F$16)*(1+DCF!$B$13)/($A18-DCF!$B$13))/(1+$A18)^DCF!$F$6)-DCF!$B$42)*1000000/DCF!$B$36/WACC!$B$20) -> 81.898649 | C18: =(((Forecast!$B$17/(1+$A18)^DCF!$B$6)+(Forecast!$C$17/(1+$A18)^DCF!$C$6)+(Forecast!$D$17/(1+$A18)^DCF!$D$6)+(Forecast!$E$17/(1+$A18)^DCF!$E$6)+((Forecast!$F$3*C$13*(1-Forecast!$F$7)+Forecast!$F$9-Forecast!$F$13-Forecast!$F$16)/(1+$A18)^DCF!$F$6)+(((Forecast!$F$3*C$13*(1-Forecast!$F$7)+Forecast!$F$9-Forecast!$F$13-Forecast!$F$16)*(1+DCF!$B$13)/($A18-DCF!$B$13))/(1+$A18)^DCF!$F$6)-DCF!$B$42)*1000000/DCF!$B$36/WACC!$B$20) -> 83.305405 | D18: =(((Forecast!$B$17/(1+$A18)^DCF!$B$6)+(Forecast!$C$17/(1+$A18)^DCF!$C$6)+(Forecast!$D$17/(1+$A18)^DCF!$D$6)+(Forecast!$E$17/(1+$A18)^DCF!$E$6)+((Forecast!$F$3*D$13*(1-Forecast!$F$7)+Forecast!$F$9-Forecast!$F$13-Forecast!$F$16)/(1+$A18)^DCF!$F$6)+(((Forecast!$F$3*D$13*(1-Forecast!$F$7)+Forecast!$F$9-Forecast!$F$13-Forecast!$F$16)*(1+DCF!$B$13)/($A18-DCF!$B$13))/(1+$A18)^DCF!$F$6)-DCF!$B$42)*1000000/DCF!$B$36/WACC!$B$20) -> 84.712161 | E18: =(((Forecast!$B$17/(1+$A18)^DCF!$B$6)+(Forecast!$C$17/(1+$A18)^DCF!$C$6)+(Forecast!$D$17/(1+$A18)^DCF!$D$6)+(Forecast!$E$17/(1+$A18)^DCF!$E$6)+((Forecast!$F$3*E$13*(1-Forecast!$F$7)+Forecast!$F$9-Forecast!$F$13-Forecast!$F$16)/(1+$A18)^DCF!$F$6)+(((Forecast!$F$3*E$13*(1-Forecast!$F$7)+Forecast!$F$9-Forecast!$F$13-Forecast!$F$16)*(1+DCF!$B$13)/($A18-DCF!$B$13))/(1+$A18)^DCF!$F$6)-DCF!$B$42)*1000000/DCF!$B$36/WACC!$B$20) -> 86.118918 | F18: =(((Forecast!$B$17/(1+$A18)^DCF!$B$6)+(Forecast!$C$17/(1+$A18)^DCF!$C$6)+(Forecast!$D$17/(1+$A18)^DCF!$D$6)+(Forecast!$E$17/(1+$A18)^DCF!$E$6)+((Forecast!$F$3*F$13*(1-Forecast!$F$7)+Forecast!$F$9-Forecast!$F$13-Forecast!$F$16)/(1+$A18)^DCF!$F$6)+(((Forecast!$F$3*F$13*(1-Forecast!$F$7)+Forecast!$F$9-Forecast!$F$13-Forecast!$F$16)*(1+DCF!$B$13)/($A18-DCF!$B$13))/(1+$A18)^DCF!$F$6)-DCF!$B$42)*1000000/DCF!$B$36/WACC!$B$20) -> 87.525674
